lifespec_fl/__init__.py
lifespec_fl/__main__.py
lifespec_fl/_version.py
lifespec_fl/cli.py
lifespec_fl/data_types.py
lifespec_fl/parser.py
lifespec_fl/data/fl_descriptor.yaml
lifespec_fl-0.0.4.dist-info/LICENSE
lifespec_fl-0.0.4.dist-info/METADATA
lifespec_fl-0.0.4.dist-info/WHEEL
lifespec_fl-0.0.4.dist-info/entry_points.txt
lifespec_fl-0.0.4.dist-info/top_level.txt
lifespec_fl-0.0.4.dist-info/RECORD
