Metadata-Version: 2.1
Name: lifespec-fl
Version: 0.0.4
Summary: .
Home-page: https://github.com/bicarlsen/lifespec_fl.git
Author: Brian Carlsen
Author-email: carlsen.bri@gmail.com
License: UNKNOWN
Keywords: lifespec,.fl,fl,file
Platform: UNKNOWN
Classifier: Programming Language :: Python :: 3
Classifier: License :: OSI Approved :: MIT License
Classifier: Operating System :: OS Independent
License-File: LICENSE
Requires-Dist: setuptools
Requires-Dist: pyyaml
Requires-Dist: numpy
Requires-Dist: pandas
Requires-Dist: parse-binary-file (>=0.0.2)
